MANIFEST.in
README.md
setup.py
src/autenticacao_api/__init__.py
src/autenticacao_api/autenticador.py
src/li_autenticador.egg-info/PKG-INFO
src/li_autenticador.egg-info/SOURCES.txt
src/li_autenticador.egg-info/dependency_links.txt
src/li_autenticador.egg-info/requires.txt
src/li_autenticador.egg-info/top_level.txt