Metadata-Version: 1.1
Name: li-autenticador
Version: 0.0.5
Summary: Engine de autenticação da Loja Integrada
Home-page: https://github.com/lojaintegrada/LI-Autenticador
Author: Loja Integrada
Author-email: suporte@lojaintegrada.com.br
License: MIT
Platform: UNKNOWN
Classifier: Development Status :: 4 - Beta
Classifier: Intended Audience :: Developers
Classifier: License :: OSI Approved :: MIT License
Classifier: Operating System :: OS Independent
Classifier: Programming Language :: Python
Classifier: Programming Language :: Python :: 2.7
Classifier: Topic :: Software Development :: Libraries :: Python Modules
Classifier: Topic :: Internet
